localmentor/__init__.py
localmentor/cli.py
localmentor/utils.py
localmentor-0.0.1.dist-info/LICENSE
localmentor-0.0.1.dist-info/METADATA
localmentor-0.0.1.dist-info/WHEEL
localmentor-0.0.1.dist-info/entry_points.txt
localmentor-0.0.1.dist-info/top_level.txt
localmentor-0.0.1.dist-info/RECORD
