Metadata-Version: 2.1
Name: localmentor
Version: 0.0.1
License-File: LICENSE
Requires-Dist: numpy
Requires-Dist: requests
